itzi/__init__.py
itzi/array_definitions.py
itzi/bmi_itzi.py
itzi/configreader.py
itzi/const.py
itzi/data_containers.py
itzi/drainage.py
itzi/flow.c
itzi/flow.cp311-win_amd64.pyd
itzi/flow.pyx
itzi/hydrology.py
itzi/infiltration.py
itzi/itzi.py
itzi/itzi_error.py
itzi/massbalance.py
itzi/messenger.py
itzi/parser.py
itzi/profiler.py
itzi/rasterdomain.py
itzi/rastermetrics.c
itzi/rastermetrics.cp311-win_amd64.pyd
itzi/rastermetrics.pyx
itzi/report.py
itzi/simulation.py
itzi/simulation_factories.py
itzi/surfaceflow.py
itzi/swmm_input_parser.py
itzi/data/example.ini
itzi/data/tutorial.ini
itzi/data/colortable/default.txt
itzi/data/colortable/depth.txt
itzi/data/colortable/froude.txt
itzi/data/colortable/vdir.txt
itzi/data/colortable/velocity.txt
itzi/providers/__init__.py
itzi/providers/base.py
itzi/providers/grass_interface.py
itzi/providers/grass_output.py
itzi/providers/memory_output.py
itzi-25.8.dist-info/licenses/LICENSE
itzi-25.8.dist-info/METADATA
itzi-25.8.dist-info/WHEEL
itzi-25.8.dist-info/entry_points.txt
itzi-25.8.dist-info/top_level.txt
itzi-25.8.dist-info/RECORD
