Metadata-Version: 2.4
Name: itzi
Version: 25.8
Summary: A distributed dynamic flood model.
Author-email: Laurent Courty <lrntct@gmail.com>
License-Expression: GPL-2.0-or-later
Project-URL: Homepage, http://www.itzi.org
Project-URL: Documentation, https://itzi.readthedocs.io
Project-URL: Repository, https://github.com/ItziModel/itzi
Project-URL: Issues, https://github.com/ItziModel/itzi/issues/
Keywords: science,engineering,hydrology,flood
Classifier: Development Status :: 4 - Beta
Classifier: Environment :: Console
Classifier: Intended Audience :: Science/Research
Classifier: Operating System :: OS Independent
Classifier: Programming Language :: Cython
Classifier: Programming Language :: Python :: 3 :: Only
Classifier: Topic :: Scientific/Engineering
Classifier: Topic :: Scientific/Engineering :: Hydrology
Requires-Python: <3.13,>=3.11
License-File: LICENSE
Requires-Dist: numpy>=2.2
Requires-Dist: pyswmm>=2.0.1
Requires-Dist: bmipy>=2.0.1
Dynamic: license-file
